nbaPlayer/__init__.py
nbaPlayer/player.py
nbaplayer-1.0.0.dist-info/LICENSE
nbaplayer-1.0.0.dist-info/METADATA
nbaplayer-1.0.0.dist-info/WHEEL
nbaplayer-1.0.0.dist-info/top_level.txt
nbaplayer-1.0.0.dist-info/RECORD
