Metadata-Version: 2.1
Name: nbaplayer
Version: 1.0.0
Summary: access stats on nba players
Home-page: https://github.com/pypa/sampleproject
Author: Brynn
Author-email: brynnengbers123@gmail.com
License: UNKNOWN
Platform: UNKNOWN
Classifier: Programming Language :: Python :: 3
Classifier: License :: OSI Approved :: MIT License
Classifier: Operating System :: OS Independent
Requires-Python: >=3.6
